reimbursements/__init__.py
reimbursements/signals.py
reimbursements/urls.py
reimbursements/views.py
reimbursements/apps/__init__.py
reimbursements/apps/reimbursements_list.py
reimbursements/apps/reimbursement_form/__init__.py
reimbursements/apps/reimbursement_form/expense_form.py
reimbursements/apps/reimbursement_form/expense_list.py
reimbursements/apps/reimbursement_form/form.py
reimbursements/migrations/__init__.py
reimbursements/models/__init__.py
reimbursements/models/expense.py
reimbursements/models/reimbursement/__init__.py
reimbursements/models/reimbursement/reimbursement.py
reimbursements/models/reimbursement/reimbursement_queryset.py
core_reimbursements-0.2.dist-info/METADATA
core_reimbursements-0.2.dist-info/WHEEL
core_reimbursements-0.2.dist-info/top_level.txt
core_reimbursements-0.2.dist-info/RECORD
