Metadata-Version: 2.1
Name: core-reimbursements
Version: 0.2
Summary: Research CORE ERM - reimbursements module
Home-page: https://github.com/research-core/core-reimbursements
Author: Ricardo Ribeiro, Hugo Cachitas
Author-email: ricardojvr@gmail.com, hugo.cachitas@research.fchampalimaud.org
License: MIT
Platform: UNKNOWN
